sejong_downloader/__init__.py
sejong_downloader/__main__.py
sejong_downloader/cli.py
sejong_downloader/downloader.py
sejong_downloader/logger.py
sejong_downloader-1.0.0.dist-info/LICENSE
sejong_downloader-1.0.0.dist-info/METADATA
sejong_downloader-1.0.0.dist-info/WHEEL
sejong_downloader-1.0.0.dist-info/entry_points.txt
sejong_downloader-1.0.0.dist-info/top_level.txt
sejong_downloader-1.0.0.dist-info/RECORD
