Metadata-Version: 2.1
Name: sejong-downloader
Version: 1.0.0
Summary: Downloader for Sejong corpus
Home-page: https://github.com/jeongukjae/sejong-downloader
Author: Jeong Ukjae
Author-email: jeongukjae@gmail.com
License: UNKNOWN
Platform: UNKNOWN
Requires-Dist: aiohttp
Requires-Dist: aiofiles
